durak/__init__.py
durak/grammar/DurakLexer.py
durak/grammar/DurakParser.py
durak/grammar/DurakParserVisitor.py
durak-0.1.4.dist-info/LICENSE
durak-0.1.4.dist-info/METADATA
durak-0.1.4.dist-info/WHEEL
durak-0.1.4.dist-info/entry_points.txt
durak-0.1.4.dist-info/top_level.txt
durak-0.1.4.dist-info/RECORD
