Metadata-Version: 2.1
Name: durak
Version: 0.1.4
Summary: HTML templating language and static site generator
Home-page: https://github.com/MasFlam/durak
Author: Łukasz Drukała
Author-email: masflam@masflam.com
License: AGPLv3
License-File: LICENSE
Requires-Dist: antlr4-python3-runtime (==4.10)
